{"donnees":[{"joueur":"BrayanWeber","indiceRestant":2,"intro":true,"tuto":false,"niveauxFinis":[true,false,false,false,false,false,false,false,false,false,false,false,false,false,false],"indiceNiveau":[false,false,false,false,false,false,false,false,false,false,false,false,false,false,false],"essaies":[2,1,1,1,1,1,1,1,1,1,1,1,1,1,1],"chronoNiveau":[501,0,0,0,0,0,0,0,0,0,0,0,0,0,0]},{"joueur":"PierrePierre","indiceRestant":2,"intro":true,"tuto":false,"niveauxFinis":[true,false,false,false,false,false,false,false,false,false,false,false,false,false,false],"indiceNiveau":[false,false,false,false,false,false,false,false,false,false,false,false,false,false,false],"essaies":[2,1,1,1,1,1,1,1,1,1,1,1,1,1,1],"chronoNiveau":[267,0,0,0,0,0,0,0,0,0,0,0,0,0,0]},{"joueur":"JeuanEufge","indiceRestant":2,"intro":true,"tuto":false,"niveauxFinis":[false,false,false,false,false,false,false,false,false,false,false,false,false,false,false],"indiceNiveau":[false,false,false,false,false,false,false,false,false,false,false,false,false,false,false],"essaies":[1,1,1,1,1,1,1,1,1,1,1,1,1,1,1],"chronoNiveau":[0,0,0,0,0,0,0,0,0,0,0,0,0,0,0]},{"joueur":"JeanEude","indiceRestant":2,"intro":true,"tuto":true,"niveauxFinis":[true,true,false,false,false,false,false,false,false,false,false,false,false,false,false],"indiceNiveau":[false,false,false,false,false,false,false,false,false,false,false,false,false,false,false],"essaies":[2,2,1,1,1,1,1,1,1,1,1,1,1,1,1],"chronoNiveau":[753,551,0,0,0,0,0,0,0,0,0,0,0,0,0]}]}